algebra_lineal/__init__.py
algebra_lineal/core.py
algebra_lineal_sheets-1.0.3.dist-info/licenses/LICENSE
algebra_lineal_sheets-1.0.3.dist-info/WHEEL
algebra_lineal_sheets-1.0.3.dist-info/METADATA
algebra_lineal_sheets-1.0.3.dist-info/RECORD
