Metadata-Version: 2.4
Name: algebra-lineal-sheets
Version: 1.0.3
Summary: Álgebra lineal simplificada con integración a Google Sheets para estudiantes
Keywords: algebra,lineal,matrices,google-sheets,educacion,estudiantes,matematicas
Author-email: Francisco Pérez Mogollón <faperez9@utpl.edu.ec>
Maintainer-email: Francisco Pérez Mogollón <faperez9@utpl.edu.ec>
Requires-Python: >=3.8
Classifier: Development Status :: 5 - Production/Stable
Classifier: Intended Audience :: Education
Classifier: Topic :: Education
Classifier: Topic :: Scientific/Engineering :: Mathematics
Classifier: Programming Language :: Python :: 3
Classifier: Programming Language :: Python :: 3.8
Classifier: Programming Language :: Python :: 3.9
Classifier: Programming Language :: Python :: 3.10
Classifier: Programming Language :: Python :: 3.11
Classifier: Programming Language :: Python :: 3.12
Classifier: Operating System :: OS Independent
Classifier: Framework :: Jupyter
License-File: LICENSE
Requires-Dist: numpy>=1.20.0
Requires-Dist: gspread>=5.0.0
Requires-Dist: google-auth>=2.0.0
Requires-Dist: google-auth-oauthlib>=0.5.0
Requires-Dist: google-auth-httplib2>=0.1.0
Requires-Dist: pytest>=6.0 ; extra == "dev"
Requires-Dist: build>=0.7.0 ; extra == "dev"
Requires-Dist: twine>=4.0.0 ; extra == "dev"
Project-URL: Documentation, https://pypi.org/project/algebra-lineal-sheets/
Project-URL: Homepage, https://pypi.org/project/algebra-lineal-sheets/
Provides-Extra: dev
